Workbook

Sheet InformacoesBasicas
A1: Esta planilha irá ajudá-lo(a) a preparar o planejamento financeiro para a sua startup. É uma planilha simplificada que exige pouca familiaridade com contabilidade ou finanças. Preencha todos os campos em "VERDE". Utilize apenas a última planilha "Resumo - Planejamento Financeiro" para demonstrar a viabilidade e lucratividade da sua empresa.
A9: Nome da Empresa: | B9: EcoTracker Tecnologia Ambiental Ltda.
A10: Atividade: | B10: 2 | C10: 1 para Comércio (posicione o cursor para ver exemplos)
C11: 2 para Serviços (posicione o cursor para ver exemplos)
C12: 3 para Indústria (posicione o cursor para ver exemplos)
A15: =IF(B10=2,"Nomes dos serviços que sua empresa irá vender","Nome dos produtos que sua empresa irá vender") -> Nomes dos serviços que sua empresa irá vender
A16: =IF(B$10=2,"Serviço","Produto") -> Serviço | B16: 1 | C16: Assinatura Premium (usuário final)
A17: =IF(B$10=2,"Serviço","Produto") -> Serviço | B17: 2 | C17: Licença B2B EcoTracker Compliance
A18: =IF(B$10=2,"Serviço","Produto") -> Serviço | B18: 3 | C18: Patrocínio / publicidade no app
A19: =IF(B$10=2,"Serviço","Produto") -> Serviço | B19: 4 | C19: Comissão de compensação de carbono
A20: =IF(B$10=2,"Serviço","Produto") -> Serviço | B20: 5
A21: =IF(B$10=2,"Serviço","Produto") -> Serviço | B21: 6
A22: =IF(B$10=2,"Serviço","Produto") -> Serviço | B22: 7
A23: =IF(B$10=2,"Serviço","Produto") -> Serviço | B23: 8
A24: =IF(B$10=2,"Serviço","Produto") -> Serviço | B24: 9
A25: =IF(B$10=2,"Serviço","Produto") -> Serviço | B25: 10
A28: Estimativa de crescimento das vendas
A29: Crescimento das vendas no Ano 02 | D29: 1
A30: Crescimento das vendas no Ano 03 | D30: 0.65
A31: Crescimento das vendas no Ano 04 | D31: 0.25
A32: Crescimento das vendas no Ano 05 | D32: 0.05
A35: Estimativa de reajustes nas despesas
A36: Reajustes nas despesas no Ano 02 | D36: 0.3
A37: Reajustes nas despesas no Ano 03 | D37: 0.15
A38: Reajustes nas despesas no Ano 04 | D38: 0.05
A39: Reajustes nas despesas no Ano 05 | D39: 0
A42: Estimativa de reajustes nos custos diretos
A43: Reajustes nas despesas no Ano 02 | D43: 0.11
A44: Reajustes nas despesas no Ano 03 | D44: 0.11
A45: Reajustes nas despesas no Ano 04 | D45: 0.11
A46: Reajustes nas despesas no Ano 05 | D46: 0.11

Sheet Entrada de $
A1: Planilha para Projeção de Vendas
A3: Custo de aquisição
A4: Mês | B4: 1 | C4: 2 | D4: 3 | E4: 4 | F4: 5 | G4: 6 | H4: 7 | I4: 8 | J4: 9 | K4: 10 | L4: 11 | M4: 12 | N4: Vendas - Ano 01
A5: Vendas Totais | B5: =B7+B11+B15+B19+B23+B27 -> 0 | C5: =C7+C11+C15+C19+C23+C27 -> 0 | D5: =D7+D11+D15+D19+D23+D27 -> 948 | E5: =E7+E11+E15+E19+E23+E27 -> 4554 | F5: =F7+F11+F15+F19+F23+F27 -> 5818 | G5: =G7+G11+G15+G19+G23+G27 -> 8130 | H5: =H7+H11+H15+H19+H23+H27 -> 13618 | I5: =I7+I11+I15+I19+I23+I27 -> 17075 | ... M5: =M7+M11+M15+M19+M23+M27 -> 39010 | N5: =SUM(B5:M5) -> 171898
A7: ="Vendas de "&InformacoesBasicas!C16 -> Vendas de Assinatura Premium (usuário final) | B7: =B8*B9 -> 0 | C7: =C8*C9 -> 0 | D7: =D8*D9 -> 948 | E7: =E8*E9 -> 2054 | F7: =F8*F9 -> 3318 | G7: =G8*G9 -> 4740 | H7: =H8*H9 -> 6478 | I7: =I8*I9 -> 8295 | ... M7: =M8*M9 -> 18170 | N7: =SUM(B7:M7) -> 82318
A8: Itens vendidos | B8: 0 | C8: 0 | D8: 120 | E8: 260 | F8: 420 | G8: 600 | H8: 820 | I8: 1050 | J8: 1300 | K8: 1600 | L8: 1950 | M8: 2300 | N8: =SUM(B8:M8) -> 10420
A9: ="Preço de "&InformacoesBasicas!C16 -> Preço de Assinatura Premium (usuário final) | B9: 7.9 | C9: 7.9 | D9: 7.9 | E9: 7.9 | F9: 7.9 | G9: 7.9 | H9: 7.9 | I9: 7.9 | J9: 7.9 | K9: 7.9 | L9: 7.9 | M9: 7.9 | N9: =SUM(B9:M9) -> 94.8
A11: ="Vendas de "&InformacoesBasicas!C17 -> Vendas de Licença B2B EcoTracker Compliance | B11: =B12*B13 -> 0 | C11: =C12*C13 -> 0 | D11: =D12*D13 -> 0 | E11: =E12*E13 -> 0 | F11: =F12*F13 -> 0 | G11: =G12*G13 -> 890 | H11: =H12*H13 -> 890 | I11: =I12*I13 -> 1780 | ... M11: =M12*M13 -> 5340 | N11: =SUM(B11:M11) -> 19580
A12: Itens vendidos | B12: 0 | C12: 0 | D12: 0 | E12: 0 | F12: 0 | G12: 1 | H12: 1 | I12: 2 | J12: 3 | K12: 4 | L12: 5 | M12: 6 | N12: =SUM(B12:M12) -> 22
A13: ="Preço de "&InformacoesBasicas!C17 -> Preço de Licença B2B EcoTracker Compliance | B13: 890 | C13: 890 | D13: 890 | E13: 890 | F13: 890 | G13: 890 | H13: 890 | I13: 890 | J13: 890 | K13: 890 | L13: 890 | M13: 890 | N13: =SUM(B13:M13) -> 10680
A15: ="Vendas de "&InformacoesBasicas!C18 -> Vendas de Patrocínio / publicidade no app | B15: =B16*B17 -> 0 | C15: =C16*C17 -> 0 | D15: =D16*D17 -> 0 | E15: =E16*E17 -> 2500 | F15: =F16*F17 -> 2500 | G15: =G16*G17 -> 2500 | H15: =H16*H17 -> 5000 | I15: =I16*I17 -> 5000 | ... M15: =M16*M17 -> 7500 | N15: =SUM(B15:M15) -> 45000
A16: Itens vendidos | B16: 0 | C16: 0 | D16: 0 | E16: 1 | F16: 1 | G16: 1 | H16: 2 | I16: 2 | J16: 2 | K16: 3 | L16: 3 | M16: 3 | N16: =SUM(B16:M16) -> 18
A17: ="Preço de "&InformacoesBasicas!C18 -> Preço de Patrocínio / publicidade no app | B17: 2500 | C17: 2500 | D17: 2500 | E17: 2500 | F17: 2500 | G17: 2500 | H17: 2500 | I17: 2500 | J17: 2500 | K17: 2500 | L17: 2500 | M17: 2500 | N17: =SUM(B17:M17) -> 30000
A19: ="Vendas de "&InformacoesBasicas!C19 -> Vendas de Comissão de compensação de carbono | B19: =B20*B21 -> 0 | C19: =C20*C21 -> 0 | D19: =D20*D21 -> 0 | E19: =E20*E21 -> 0 | F19: =F20*F21 -> 0 | G19: =G20*G21 -> 0 | H19: =H20*H21 -> 1250 | I19: =I20*I21 -> 2000 | ... M19: =M20*M21 -> 8000 | N19: =SUM(B19:M19) -> 25000
A20: Itens vendidos | B20: 0 | C20: 0 | D20: 0 | E20: 0 | F20: 0 | G20: 0 | H20: 50 | I20: 80 | J20: 120 | K20: 180 | L20: 250 | M20: 320 | N20: =SUM(B20:M20) -> 1000
A21: ="Preço de "&InformacoesBasicas!C19 -> Preço de Comissão de compensação de carbono | B21: 25 | C21: 25 | D21: 25 | E21: 25 | F21: 25 | G21: 25 | H21: 25 | I21: 25 | J21: 25 | K21: 25 | L21: 25 | M21: 25 | N21: =SUM(B21:M21) -> 300
A23: ="Vendas de "&InformacoesBasicas!C20 -> Vendas de | B23: =B24*B25 -> 0 | C23: =C24*C25 -> 0 | D23: =D24*D25 -> 0 | E23: =E24*E25 -> 0 | F23: =F24*F25 -> 0 | G23: =G24*G25 -> 0 | H23: =H24*H25 -> 0 | I23: =I24*I25 -> 0 | ... M23: =M24*M25 -> 0 | N23: =SUM(B23:M23) -> 0
A24: Itens vendidos | B24: 0 | C24: 0 | D24: 0 | E24: 0 | F24: 0 | G24: 0 | H24: 0 | I24: 0 | J24: 0 | K24: 0 | L24: 0 | M24: 0 | N24: =SUM(B24:M24) -> 0
A25: ="Preço de "&InformacoesBasicas!C20 -> Preço de | B25: 0 | C25: 0 | D25: 0 | E25: 0 | F25: 0 | G25: 0 | H25: 0 | I25: 0 | J25: 0 | K25: 0 | L25: 0 | M25: 0 | N25: =SUM(B25:M25) -> 0
A27: ="Vendas de "&InformacoesBasicas!C21 -> Vendas de | B27: =B28*B29 -> 0 | C27: =C28*C29 -> 0 | D27: =D28*D29 -> 0 | E27: =E28*E29 -> 0 | F27: =F28*F29 -> 0 | G27: =G28*G29 -> 0 | H27: =H28*H29 -> 0 | I27: =I28*I29 -> 0 | ... M27: =M28*M29 -> 0 | N27: =SUM(B27:M27) -> 0
A28: Itens vendidos | B28: 0 | C28: 0 | D28: 0 | E28: 0 | F28: 0 | G28: 0 | H28: 0 | I28: 0 | J28: 0 | K28: 0 | L28: 0 | M28: 0 | N28: =SUM(B28:M28) -> 0
A29: ="Preço de "&InformacoesBasicas!C21 -> Preço de | B29: 0 | C29: 0 | D29: 0 | E29: 0 | F29: 0 | G29: 0 | H29: 0 | I29: 0 | J29: 0 | K29: 0 | L29: 0 | M29: 0 | N29: =SUM(B29:M29) -> 0
A31: ="Vendas de "&InformacoesBasicas!C22 -> Vendas de | B31: =B32*B33 -> 0 | C31: =C32*C33 -> 0 | D31: =D32*D33 -> 0 | E31: =E32*E33 -> 0 | F31: =F32*F33 -> 0 | G31: =G32*G33 -> 0 | H31: =H32*H33 -> 0 | I31: =I32*I33 -> 0 | ... M31: =M32*M33 -> 0 | N31: =SUM(B31:M31) -> 0
A32: Itens vendidos | B32: 0 | C32: 0 | D32: 0 | E32: 0 | F32: 0 | G32: 0 | H32: 0 | I32: 0 | J32: 0 | K32: 0 | L32: 0 | M32: 0 | N32: =SUM(B32:M32) -> 0
A33: ="Preço de "&InformacoesBasicas!C25 -> Preço de | B33: 0 | C33: 0 | D33: 0 | E33: 0 | F33: 0 | G33: 0 | H33: 0 | I33: 0 | J33: 0 | K33: 0 | L33: 0 | M33: 0 | N33: =SUM(B33:M33) -> 0
A35: ="Vendas de "&InformacoesBasicas!C23 -> Vendas de | B35: =B36*B37 -> 0 | C35: =C36*C37 -> 0 | D35: =D36*D37 -> 0 | E35: =E36*E37 -> 0 | F35: =F36*F37 -> 0 | G35: =G36*G37 -> 0 | H35: =H36*H37 -> 0 | I35: =I36*I37 -> 0 | ... M35: =M36*M37 -> 0 | N35: =SUM(B35:M35) -> 0
A36: Itens vendidos | B36: 0 | C36: 0 | D36: 0 | E36: 0 | F36: 0 | G36: 0 | H36: 0 | I36: 0 | J36: 0 | K36: 0 | L36: 0 | M36: 0 | N36: =SUM(B36:M36) -> 0
A37: ="Preço de "&InformacoesBasicas!C29 -> Preço de | B37: 0 | C37: 0 | D37: 0 | E37: 0 | F37: 0 | G37: 0 | H37: 0 | I37: 0 | J37: 0 | K37: 0 | L37: 0 | M37: 0 | N37: =SUM(B37:M37) -> 0
A39: ="Vendas de "&InformacoesBasicas!C24 -> Vendas de | B39: =B40*B41 -> 0 | C39: =C40*C41 -> 0 | D39: =D40*D41 -> 0 | E39: =E40*E41 -> 0 | F39: =F40*F41 -> 0 | G39: =G40*G41 -> 0 | H39: =H40*H41 -> 0 | I39: =I40*I41 -> 0 | ... M39: =M40*M41 -> 0 | N39: =SUM(B39:M39) -> 0
A40: Itens vendidos | B40: 0 | C40: 0 | D40: 0 | E40: 0 | F40: 0 | G40: 0 | H40: 0 | I40: 0 | J40: 0 | K40: 0 | L40: 0 | M40: 0 | N40: =SUM(B40:M40) -> 0
A41: ="Preço de "&InformacoesBasicas!C33 -> Preço de | B41: 0 | C41: 0 | D41: 0 | E41: 0 | F41: 0 | G41: 0 | H41: 0 | I41: 0 | J41: 0 | K41: 0 | L41: 0 | M41: 0 | N41: =SUM(B41:M41) -> 0
A43: ="Vendas de "&InformacoesBasicas!C25 -> Vendas de | B43: =B44*B45 -> 0 | C43: =C44*C45 -> 0 | D43: =D44*D45 -> 0 | E43: =E44*E45 -> 0 | F43: =F44*F45 -> 0 | G43: =G44*G45 -> 0 | H43: =H44*H45 -> 0 | I43: =I44*I45 -> 0 | ... M43: =M44*M45 -> 0 | N43: =SUM(B43:M43) -> 0
A44: Itens vendidos | B44: 0 | C44: 0 | D44: 0 | E44: 0 | F44: 0 | G44: 0 | H44: 0 | I44: 0 | J44: 0 | K44: 0 | L44: 0 | M44: 0 | N44: =SUM(B44:M44) -> 0
A45: ="Preço de "&InformacoesBasicas!C37 -> Preço de | B45: 0 | C45: 0 | D45: 0 | E45: 0 | F45: 0 | G45: 0 | H45: 0 | I45: 0 | J45: 0 | K45: 0 | L45: 0 | M45: 0 | N45: =SUM(B45:M45) -> 0

Sheet Custo Unitário
A1: Planilha para Cálculo do Custo Unitário
A4: =IF(InformacoesBasicas!B10=1,"Custo Unitário Médio de Aquisição do Fornecedor de ",IF(InformacoesBasicas!B10=2,"Custo Unitário de Prestação de cada Serviço de ",IF(InformacoesBasicas!B10=3,"Custo da matéria-prima para Fabricação de cada ","Custo de")))&InformacoesBasicas!C16 -> Custo Unitário de Prestação de cada Serviço de Assinatura Premium (usuário final) | B4: 1.1
A6: =IF(InformacoesBasicas!B10=1,"Custo Médio de Aquisição do Fornecedor de ",IF(InformacoesBasicas!B10=2,"Custo Unitário de Prestação de cada Serviço de ",IF(InformacoesBasicas!B10=3,"Custo da matéria-prima para Fabricação de cada ","Custo de")))&InformacoesBasicas!C17 -> Custo Unitário de Prestação de cada Serviço de Licença B2B EcoTracker Compliance | B6: 120
A8: =IF(InformacoesBasicas!B10=1,"Custo Médio de Aquisição do Fornecedor de ",IF(InformacoesBasicas!B10=2,"Custo Unitário de Prestação de cada Serviço de ",IF(InformacoesBasicas!B10=3,"Custo da matéria-prima para Fabricação de cada ","Custo de")))&InformacoesBasicas!C18 -> Custo Unitário de Prestação de cada Serviço de Patrocínio / publicidade no app | B8: 300
A10: =IF(InformacoesBasicas!B10=1,"Custo Médio de Aquisição do Fornecedor de ",IF(InformacoesBasicas!B10=2,"Custo Unitário de Prestação de cada Serviço de ",IF(InformacoesBasicas!B10=3,"Custo da matéria-prima para Fabricação de cada ","Custo de")))&InformacoesBasicas!C19 -> Custo Unitário de Prestação de cada Serviço de Comissão de compensação de carbono | B10: 15
A12: =IF(InformacoesBasicas!B10=1,"Custo Médio de Aquisição do Fornecedor de ",IF(InformacoesBasicas!B10=2,"Custo Unitário de Prestação de cada Serviço de ",IF(InformacoesBasicas!B10=3,"Custo da matéria-prima para Fabricação de cada ","Custo de")))&InformacoesBasicas!C20 -> Custo Unitário de Prestação de cada Serviço de | B12: 0
A14: =IF(InformacoesBasicas!B10=1,"Custo Médio de Aquisição do Fornecedor de ",IF(InformacoesBasicas!B10=2,"Custo Unitário de Prestação de cada Serviço de ",IF(InformacoesBasicas!B10=3,"Custo da matéria-prima para Fabricação de cada ","Custo de")))&InformacoesBasicas!C21 -> Custo Unitário de Prestação de cada Serviço de | B14: 0
A16: =IF(InformacoesBasicas!B10=1,"Custo Médio de Aquisição do Fornecedor de ",IF(InformacoesBasicas!B10=2,"Custo Unitário de Prestação de cada Serviço de ",IF(InformacoesBasicas!B10=3,"Custo da matéria-prima para Fabricação de cada ","Custo de")))&InformacoesBasicas!C22 -> Custo Unitário de Prestação de cada Serviço de | B16: 0
A18: =IF(InformacoesBasicas!B10=1,"Custo Médio de Aquisição do Fornecedor de ",IF(InformacoesBasicas!B10=2,"Custo Unitário de Prestação de cada Serviço de ",IF(InformacoesBasicas!B10=3,"Custo da matéria-prima para Fabricação de cada ","Custo de")))&InformacoesBasicas!C23 -> Custo Unitário de Prestação de cada Serviço de | B18: 0
A20: =IF(InformacoesBasicas!B10=1,"Custo Médio de Aquisição do Fornecedor de ",IF(InformacoesBasicas!B10=2,"Custo Unitário de Prestação de cada Serviço de ",IF(InformacoesBasicas!B10=3,"Custo da matéria-prima para Fabricação de cada ","Custo de")))&InformacoesBasicas!C24 -> Custo Unitário de Prestação de cada Serviço de | B20: 0
A22: =IF(InformacoesBasicas!B10=1,"Custo Médio de Aquisição do Fornecedor de ",IF(InformacoesBasicas!B10=2,"Custo Unitário de Prestação de cada Serviço de ",IF(InformacoesBasicas!B10=3,"Custo da matéria-prima para Fabricação de cada ","Custo de")))&InformacoesBasicas!C25 -> Custo Unitário de Prestação de cada Serviço de | B22: 0

Sheet Calculo de Custo
A1: Planilha para Cálculo do Custo Total
A4: Mês | B4: 1 | C4: 2 | D4: 3 | E4: 4 | F4: 5 | G4: 6 | H4: 7 | I4: 8 | J4: 9 | K4: 10 | L4: 11 | M4: 12 | N4: Vendas - Ano 01
A5: Assinaturas ativas | B5: =B10+B14+B18 -> 0 | C5: =C10+C14+C18 -> 0 | D5: =D10+D14+D18 -> 120 | E5: =E10+E14+E18 -> 261 | F5: =F10+F14+F18 -> 421 | G5: =G10+G14+G18 -> 602 | H5: =H10+H14+H18 -> 823 | I5: =I10+I14+I18 -> 1054 | ... N5: =N10+N14+N18 -> 10460
A6: Vendas Totais | B6: =B8+B12+B16+B20+B24+B28+B32+B36+B40+B44 -> 0 | C6: =C8+C12+C16+C20+C24+C28+C32+C36+C40+C44 -> 0 | D6: =D8+D12+D16+D20+D24+D28+D32+D36+D40+D44 -> 132 | E6: =E8+E12+E16+E20+E24+E28+E32+E36+E40+E44 -> 586 | F6: =F8+F12+F16+F20+F24+F28+F32+F36+F40+F44 -> 762 | G6: =G8+G12+G16+G20+G24+G28+G32+G36+G40+G44 -> 1080 | H6: =H8+H12+H16+H20+H24+H28+H32+H36+H40+H44 -> 2372 | I6: =I8+I12+I16+I20+I24+I28+I32+I36+I40+I44 -> 3195 | ... N6: =N8+N12+N16+N20+N24+N28+N32+N36+N40+N44 -> 34502
A8: ="Custo Total de "&InformacoesBasicas!C16 -> Custo Total de Assinatura Premium (usuário final) | B8: =B9*B10 -> 0 | C8: =C9*C10 -> 0 | D8: =D9*D10 -> 132 | E8: =E9*E10 -> 286 | F8: =F9*F10 -> 462 | G8: =G9*G10 -> 660 | H8: =H9*H10 -> 902 | I8: =I9*I10 -> 1155 | ... M8: =M9*M10 -> 2530 | N8: =SUM(B8:M8) -> 11462
A9: =IF(InformacoesBasicas!B10=1,"Custo de Aquisição de ",IF(InformacoesBasicas!B10=2,"Custo de Prestação de Serviço de ",IF(InformacoesBasicas!B10=3,"Custo de Fabricação de ","Custo de")))&InformacoesBasicas!C16 -> Custo de Prestação de Serviço de Assinatura Premium (usuário final) | B9: ='Custo Unitário'!B4 -> 1.1 | C9: =$B9 -> 1.1 | D9: =$B9 -> 1.1 | E9: =$B9 -> 1.1 | F9: =$B9 -> 1.1 | G9: =$B9 -> 1.1 | H9: =$B9 -> 1.1 | I9: =$B9 -> 1.1 | J9: =$B9 -> 1.1 | ... M9: =$B9 -> 1.1 | N9: =AVERAGE(B9:L9) -> 1.1
A10: Itens vendidos | B10: ='Entrada de $'!B8 -> 0 | C10: ='Entrada de $'!C8 -> 0 | D10: ='Entrada de $'!D8 -> 120 | E10: ='Entrada de $'!E8 -> 260 | F10: ='Entrada de $'!F8 -> 420 | G10: ='Entrada de $'!G8 -> 600 | H10: ='Entrada de $'!H8 -> 820 | I10: ='Entrada de $'!I8 -> 1050 | ... M10: ='Entrada de $'!M8 -> 2300 | N10: =SUM(B10:M10) -> 10420
A12: ="Custo Total de "&InformacoesBasicas!C17 -> Custo Total de Licença B2B EcoTracker Compliance | B12: =B13*B14 -> 0 | C12: =C13*C14 -> 0 | D12: =D13*D14 -> 0 | E12: =E13*E14 -> 0 | F12: =F13*F14 -> 0 | G12: =G13*G14 -> 120 | H12: =H13*H14 -> 120 | I12: =I13*I14 -> 240 | ... M12: =M13*M14 -> 720 | N12: =SUM(B12:M12) -> 2640
A13: =IF(InformacoesBasicas!B10=1,"Custo de Aquisição de ",IF(InformacoesBasicas!B10=2,"Custo de Prestação de Serviço de ",IF(InformacoesBasicas!B10=3,"Custo de Fabricação de ","Custo de")))&InformacoesBasicas!C17 -> Custo de Prestação de Serviço de Licença B2B EcoTracker Compliance | B13: ='Custo Unitário'!B6 -> 120 | C13: =$B13 -> 120 | D13: =$B13 -> 120 | E13: =$B13 -> 120 | F13: =$B13 -> 120 | G13: =$B13 -> 120 | H13: =$B13 -> 120 | I13: =$B13 -> 120 | J13: =$B13 -> 120 | ... M13: =$B13 -> 120 | N13: =AVERAGE(B13:L13) -> 120
A14: Itens vendidos | B14: ='Entrada de $'!B12 -> 0 | C14: ='Entrada de $'!C12 -> 0 | D14: ='Entrada de $'!D12 -> 0 | E14: ='Entrada de $'!E12 -> 0 | F14: ='Entrada de $'!F12 -> 0 | G14: ='Entrada de $'!G12 -> 1 | H14: ='Entrada de $'!H12 -> 1 | I14: ='Entrada de $'!I12 -> 2 | ... M14: ='Entrada de $'!M12 -> 6 | N14: =SUM(B14:M14) -> 22
A16: ="Custo Total de "&InformacoesBasicas!C18 -> Custo Total de Patrocínio / publicidade no app | B16: =B17*B18 -> 0 | C16: =C17*C18 -> 0 | D16: =D17*D18 -> 0 | E16: =E17*E18 -> 300 | F16: =F17*F18 -> 300 | G16: =G17*G18 -> 300 | H16: =H17*H18 -> 600 | I16: =I17*I18 -> 600 | ... M16: =M17*M18 -> 900 | N16: =SUM(B16:M16) -> 5400
A17: =IF(InformacoesBasicas!B10=1,"Custo de Aquisição de ",IF(InformacoesBasicas!B10=2,"Custo de Prestação de Serviço de ",IF(InformacoesBasicas!B10=3,"Custo de Fabricação de ","Custo de")))&InformacoesBasicas!C18 -> Custo de Prestação de Serviço de Patrocínio / publicidade no app | B17: ='Custo Unitário'!B8 -> 300 | C17: =$B17 -> 300 | D17: =$B17 -> 300 | E17: =$B17 -> 300 | F17: =$B17 -> 300 | G17: =$B17 -> 300 | H17: =$B17 -> 300 | I17: =$B17 -> 300 | J17: =$B17 -> 300 | ... M17: =$B17 -> 300 | N17: =AVERAGE(B17:L17) -> 300
A18: Itens vendidos | B18: ='Entrada de $'!B16 -> 0 | C18: ='Entrada de $'!C16 -> 0 | D18: ='Entrada de $'!D16 -> 0 | E18: ='Entrada de $'!E16 -> 1 | F18: ='Entrada de $'!F16 -> 1 | G18: ='Entrada de $'!G16 -> 1 | H18: ='Entrada de $'!H16 -> 2 | I18: ='Entrada de $'!I16 -> 2 | ... M18: ='Entrada de $'!M16 -> 3 | N18: =SUM(B18:M18) -> 18
A20: ="Custo Total de "&InformacoesBasicas!C19 -> Custo Total de Comissão de compensação de carbono | B20: =B21*B22 -> 0 | C20: =C21*C22 -> 0 | D20: =D21*D22 -> 0 | E20: =E21*E22 -> 0 | F20: =F21*F22 -> 0 | G20: =G21*G22 -> 0 | H20: =H21*H22 -> 750 | I20: =I21*I22 -> 1200 | ... M20: =M21*M22 -> 4800 | N20: =SUM(B20:M20) -> 15000
A21: =IF(InformacoesBasicas!B10=1,"Custo de Aquisição de ",IF(InformacoesBasicas!B10=2,"Custo de Prestação de Serviço de ",IF(InformacoesBasicas!B10=3,"Custo de Fabricação de ","Custo de")))&InformacoesBasicas!C19 -> Custo de Prestação de Serviço de Comissão de compensação de carbono | B21: ='Custo Unitário'!B10 -> 15 | C21: =$B21 -> 15 | D21: =$B21 -> 15 | E21: =$B21 -> 15 | F21: =$B21 -> 15 | G21: =$B21 -> 15 | H21: =$B21 -> 15 | I21: =$B21 -> 15 | J21: =$B21 -> 15 | ... M21: =$B21 -> 15 | N21: =AVERAGE(B21:L21) -> 15
A22: Itens vendidos | B22: ='Entrada de $'!B20 -> 0 | C22: ='Entrada de $'!C20 -> 0 | D22: ='Entrada de $'!D20 -> 0 | E22: ='Entrada de $'!E20 -> 0 | F22: ='Entrada de $'!F20 -> 0 | G22: ='Entrada de $'!G20 -> 0 | H22: ='Entrada de $'!H20 -> 50 | I22: ='Entrada de $'!I20 -> 80 | ... M22: ='Entrada de $'!M20 -> 320 | N22: =SUM(B22:M22) -> 1000
A24: ="Custo Total de "&InformacoesBasicas!C20 -> Custo Total de | B24: =B25*B26 -> 0 | C24: =C25*C26 -> 0 | D24: =D25*D26 -> 0 | E24: =E25*E26 -> 0 | F24: =F25*F26 -> 0 | G24: =G25*G26 -> 0 | H24: =H25*H26 -> 0 | I24: =I25*I26 -> 0 | ... M24: =M25*M26 -> 0 | N24: =SUM(B24:M24) -> 0
A25: =IF(InformacoesBasicas!B10=1,"Custo de Aquisição de ",IF(InformacoesBasicas!B10=2,"Custo de Prestação de Serviço de ",IF(InformacoesBasicas!B10=3,"Custo de Fabricação de ","Custo de")))&InformacoesBasicas!C20 -> Custo de Prestação de Serviço de | B25: ='Custo Unitário'!B18 -> 0 | C25: =$B25 -> 0 | D25: =$B25 -> 0 | E25: =$B25 -> 0 | F25: =$B25 -> 0 | G25: =$B25 -> 0 | H25: =$B25 -> 0 | I25: =$B25 -> 0 | J25: =$B25 -> 0 | ... M25: =$B25 -> 0 | N25: =AVERAGE(B25:L25) -> 0
A26: Itens vendidos | B26: ='Entrada de $'!B24 -> 0 | C26: ='Entrada de $'!C24 -> 0 | D26: ='Entrada de $'!D24 -> 0 | E26: ='Entrada de $'!E24 -> 0 | F26: ='Entrada de $'!F24 -> 0 | G26: ='Entrada de $'!G24 -> 0 | H26: ='Entrada de $'!H24 -> 0 | I26: ='Entrada de $'!I24 -> 0 | ... M26: ='Entrada de $'!M24 -> 0 | N26: =SUM(B26:M26) -> 0
A28: ="Custo Total de "&InformacoesBasicas!C21 -> Custo Total de | B28: =B29*B30 -> 0 | C28: =C29*C30 -> 0 | D28: =D29*D30 -> 0 | E28: =E29*E30 -> 0 | F28: =F29*F30 -> 0 | G28: =G29*G30 -> 0 | H28: =H29*H30 -> 0 | I28: =I29*I30 -> 0 | ... M28: =M29*M30 -> 0 | N28: =SUM(B28:M28) -> 0
A29: =IF(InformacoesBasicas!B10=1,"Custo de Aquisição de ",IF(InformacoesBasicas!B10=2,"Custo de Prestação de Serviço de ",IF(InformacoesBasicas!B10=3,"Custo de Fabricação de ","Custo de")))&InformacoesBasicas!C21 -> Custo de Prestação de Serviço de | B29: ='Custo Unitário'!B22 -> 0 | C29: =$B29 -> 0 | D29: =$B29 -> 0 | E29: =$B29 -> 0 | F29: =$B29 -> 0 | G29: =$B29 -> 0 | H29: =$B29 -> 0 | I29: =$B29 -> 0 | J29: =$B29 -> 0 | ... M29: =$B29 -> 0 | N29: =AVERAGE(B29:L29) -> 0
A30: Itens vendidos | B30: ='Entrada de $'!B28 -> 0 | C30: ='Entrada de $'!C28 -> 0 | D30: ='Entrada de $'!D28 -> 0 | E30: ='Entrada de $'!E28 -> 0 | F30: ='Entrada de $'!F28 -> 0 | G30: ='Entrada de $'!G28 -> 0 | H30: ='Entrada de $'!H28 -> 0 | I30: ='Entrada de $'!I28 -> 0 | ... M30: ='Entrada de $'!M28 -> 0 | N30: =SUM(B30:M30) -> 0
A32: ="Custo Total de "&InformacoesBasicas!C22 -> Custo Total de | B32: =B33*B34 -> 0 | C32: =C33*C34 -> 0 | D32: =D33*D34 -> 0 | E32: =E33*E34 -> 0 | F32: =F33*F34 -> 0 | G32: =G33*G34 -> 0 | H32: =H33*H34 -> 0 | I32: =I33*I34 -> 0 | ... M32: =M33*M34 -> 0 | N32: =SUM(B32:M32) -> 0
A33: =IF(InformacoesBasicas!B10=1,"Custo de Aquisição de ",IF(InformacoesBasicas!B10=2,"Custo de Prestação de Serviço de ",IF(InformacoesBasicas!B10=3,"Custo de Fabricação de ","Custo de")))&InformacoesBasicas!C22 -> Custo de Prestação de Serviço de | B33: ='Custo Unitário'!B26 -> 0 | C33: =$B33 -> 0 | D33: =$B33 -> 0 | E33: =$B33 -> 0 | F33: =$B33 -> 0 | G33: =$B33 -> 0 | H33: =$B33 -> 0 | I33: =$B33 -> 0 | J33: =$B33 -> 0 | ... M33: =$B33 -> 0 | N33: =AVERAGE(B33:L33) -> 0
A34: Itens vendidos | B34: ='Entrada de $'!B32 -> 0 | C34: ='Entrada de $'!C32 -> 0 | D34: ='Entrada de $'!D32 -> 0 | E34: ='Entrada de $'!E32 -> 0 | F34: ='Entrada de $'!F32 -> 0 | G34: ='Entrada de $'!G32 -> 0 | H34: ='Entrada de $'!H32 -> 0 | I34: ='Entrada de $'!I32 -> 0 | ... M34: ='Entrada de $'!M32 -> 0 | N34: =SUM(B34:M34) -> 0
A36: ="Custo Total de "&InformacoesBasicas!C23 -> Custo Total de | B36: =B37*B38 -> 0 | C36: =C37*C38 -> 0 | D36: =D37*D38 -> 0 | E36: =E37*E38 -> 0 | F36: =F37*F38 -> 0 | G36: =G37*G38 -> 0 | H36: =H37*H38 -> 0 | I36: =I37*I38 -> 0 | ... M36: =M37*M38 -> 0 | N36: =SUM(B36:M36) -> 0
A37: =IF(InformacoesBasicas!B10=1,"Custo de Aquisição de ",IF(InformacoesBasicas!B10=2,"Custo de Prestação de Serviço de ",IF(InformacoesBasicas!B10=3,"Custo de Fabricação de ","Custo de")))&InformacoesBasicas!C23 -> Custo de Prestação de Serviço de | B37: ='Custo Unitário'!B30 -> 0 | C37: =$B37 -> 0 | D37: =$B37 -> 0 | E37: =$B37 -> 0 | F37: =$B37 -> 0 | G37: =$B37 -> 0 | H37: =$B37 -> 0 | I37: =$B37 -> 0 | J37: =$B37 -> 0 | ... M37: =$B37 -> 0 | N37: =AVERAGE(B37:L37) -> 0
A38: Itens vendidos | B38: ='Entrada de $'!B36 -> 0 | C38: ='Entrada de $'!C36 -> 0 | D38: ='Entrada de $'!D36 -> 0 | E38: ='Entrada de $'!E36 -> 0 | F38: ='Entrada de $'!F36 -> 0 | G38: ='Entrada de $'!G36 -> 0 | H38: ='Entrada de $'!H36 -> 0 | I38: ='Entrada de $'!I36 -> 0 | ... M38: ='Entrada de $'!M36 -> 0 | N38: =SUM(B38:M38) -> 0
A40: ="Custo Total de "&InformacoesBasicas!C24 -> Custo Total de | B40: =B41*B42 -> 0 | C40: =C41*C42 -> 0 | D40: =D41*D42 -> 0 | E40: =E41*E42 -> 0 | F40: =F41*F42 -> 0 | G40: =G41*G42 -> 0 | H40: =H41*H42 -> 0 | I40: =I41*I42 -> 0 | ... M40: =M41*M42 -> 0 | N40: =SUM(B40:M40) -> 0
A41: =IF(InformacoesBasicas!B10=1,"Custo de Aquisição de ",IF(InformacoesBasicas!B10=2,"Custo de Prestação de Serviço de ",IF(InformacoesBasicas!B10=3,"Custo de Fabricação de ","Custo de")))&InformacoesBasicas!C24 -> Custo de Prestação de Serviço de | B41: ='Custo Unitário'!B34 -> 0 | C41: =$B41 -> 0 | D41: =$B41 -> 0 | E41: =$B41 -> 0 | F41: =$B41 -> 0 | G41: =$B41 -> 0 | H41: =$B41 -> 0 | I41: =$B41 -> 0 | J41: =$B41 -> 0 | ... M41: =$B41 -> 0 | N41: =AVERAGE(B41:L41) -> 0
A42: Itens vendidos | B42: ='Entrada de $'!B40 -> 0 | C42: ='Entrada de $'!C40 -> 0 | D42: ='Entrada de $'!D40 -> 0 | E42: ='Entrada de $'!E40 -> 0 | F42: ='Entrada de $'!F40 -> 0 | G42: ='Entrada de $'!G40 -> 0 | H42: ='Entrada de $'!H40 -> 0 | I42: ='Entrada de $'!I40 -> 0 | ... M42: ='Entrada de $'!M40 -> 0 | N42: =SUM(B42:M42) -> 0
A44: ="Custo Total de "&InformacoesBasicas!C25 -> Custo Total de | B44: =B45*B46 -> 0 | C44: =C45*C46 -> 0 | D44: =D45*D46 -> 0 | E44: =E45*E46 -> 0 | F44: =F45*F46 -> 0 | G44: =G45*G46 -> 0 | H44: =H45*H46 -> 0 | I44: =I45*I46 -> 0 | ... M44: =M45*M46 -> 0 | N44: =SUM(B44:M44) -> 0
A45: =IF(InformacoesBasicas!B10=1,"Custo de Aquisição de ",IF(InformacoesBasicas!B10=2,"Custo de Prestação de Serviço de ",IF(InformacoesBasicas!B10=3,"Custo de Fabricação de ","Custo de")))&InformacoesBasicas!C25 -> Custo de Prestação de Serviço de | B45: ='Custo Unitário'!B38 -> 0 | C45: =$B45 -> 0 | D45: =$B45 -> 0 | E45: =$B45 -> 0 | F45: =$B45 -> 0 | G45: =$B45 -> 0 | H45: =$B45 -> 0 | I45: =$B45 -> 0 | J45: =$B45 -> 0 | ... M45: =$B45 -> 0 | N45: =AVERAGE(B45:L45) -> 0
A46: Itens vendidos | B46: ='Entrada de $'!B44 -> 0 | C46: ='Entrada de $'!C44 -> 0 | D46: ='Entrada de $'!D44 -> 0 | E46: ='Entrada de $'!E44 -> 0 | F46: ='Entrada de $'!F44 -> 0 | G46: ='Entrada de $'!G44 -> 0 | H46: ='Entrada de $'!H44 -> 0 | I46: ='Entrada de $'!I44 -> 0 | ... M46: ='Entrada de $'!M44 -> 0 | N46: =SUM(B46:M46) -> 0

Sheet Saídas de $
A1: Estimativa de Saídas de Caixa com Gastos Pré-Operacionais e Despesas Operacionais
A4: Mês | B4: 0 | D4: 1 | E4: 2 | F4: 3 | G4: 4 | H4: 5 | I4: 6 | J4: 7 | K4: 8 | L4: 9 | M4: 10 | N4: 11 | O4: 12 | P4: Gastos e Despesas - Ano 01
A5: Total de Saída de Caixa | B5: =B8 -> 143800 | D5: =D22 -> 14470 | E5: =E22 -> 14470 | F5: =F22 -> 14610 | G5: =G22 -> 16200 | H5: =H22 -> 16650 | I5: =I22 -> 16860 | J5: =J22 -> 22030 | K5: =K22 -> 22200 | ... O5: =O22 -> 24900 | P5: =SUM(D5:O5) -> 235840
C7: Depreciação
A8: Gastos para criar a empresa | B8: =SUM(B9:B20) -> 143800
A9: Gastos com documentação | B9: 1800
A10: Gastos com máquinas e equipamentos | B10: 12000 | C10: =B10*0.2 -> 2400
A11: Gastos com reforma do imóvel | B11: 0 | C11: =B11*0.01 -> 0
A12: Gastos com móveis e utensílios | B12: 3000 | C12: =B12*0.2 -> 600
A13: Gastos com estoque inicial | B13: 0
A14: Outros gastos pré-operacionais | B14: 2500
A15: Advogado | B15: 3500
A16: Desenvolvimento App Android | B16: 45000
A17: Desenvolvimento App IoS | B17: 38000
A18: Desenvolvimento Site | B18: 6000
A19: Sistema Web | B19: 32000
A22: Despesas com a operação | D22: =SUM(D23:D34) -> 14470 | E22: =SUM(E23:E34) -> 14470 | F22: =SUM(F23:F34) -> 14610 | G22: =SUM(G23:G34) -> 16200 | H22: =SUM(H23:H34) -> 16650 | I22: =SUM(I23:I34) -> 16860 | J22: =SUM(J23:J34) -> 22030 | K22: =SUM(K23:K34) -> 22200 | ... O22: =SUM(O23:O34) -> 24900 | P22: =SUM(D22:O22) -> 235840
A23: Despesas com salários | D23: 8000 | E23: 8000 | F23: 8000 | G23: 8000 | H23: 8000 | I23: 8000 | J23: 12000 | K23: 12000 | L23: 12000 | M23: 12000 | N23: 12000 | O23: 12000 | P23: =SUM(D23:O23) -> 120000
A24: Retirada dos sócios | D24: 2500 | E24: 2500 | F24: 2500 | G24: 2500 | H24: 2500 | I24: 2500 | J24: 2500 | K24: 2500 | L24: 2500 | M24: 2500 | N24: 2500 | O24: 2500 | P24: =SUM(D24:O24) -> 30000
A25: Comissões Vendas | D25: 0 | E25: 0 | F25: 100 | G25: 150 | H25: 250 | I25: 400 | J25: 600 | K25: 700 | L25: 800 | M25: 900 | N25: 1000 | O25: 1100 | P25: =SUM(D25:O25) -> 6000
A26: Investimento em Marketing | D26: 2000 | E26: 2000 | F26: 2000 | G26: 3500 | H26: 3500 | I26: 3500 | J26: 3500 | K26: 3500 | L26: 5000 | M26: 5000 | N26: 5000 | O26: 5000 | P26: =SUM(D26:O26) -> 43500
A27: Processadoras de pagamento | D27: 0 | E27: 0 | F27: 40 | G27: 80 | H27: 130 | I27: 190 | J27: 260 | K27: 330 | L27: 410 | M27: 510 | N27: 620 | O27: 730 | P27: =SUM(D27:O27) -> 3300
A28: Hospedagem | D28: 400 | E28: 400 | F28: 400 | G28: 400 | H28: 700 | I28: 700 | J28: 700 | K28: 700 | L28: 1100 | M28: 1100 | N28: 1100 | O28: 1100 | P28: =SUM(D28:O28) -> 8800
A29: Despesas com serviços | D29: 800 | E29: 800 | F29: 800 | G29: 800 | H29: 800 | I29: 800 | J29: 800 | K29: 800 | L29: 800 | M29: 800 | N29: 800 | O29: 800 | P29: =SUM(D29:O29) -> 9600
A30: Aluguel | D30: 0 | E30: 0 | F30: 0 | G30: 0 | H30: 0 | I30: 0 | J30: 900 | K30: 900 | L30: 900 | M30: 900 | N30: 900 | O30: 900 | P30: =SUM(D30:O30) -> 5400
A31: Água | D31: 0 | E31: 0 | F31: 0 | G31: 0 | H31: 0 | I31: 0 | J31: 0 | K31: 0 | L31: 0 | M31: 0 | N31: 0 | O31: 0 | P31: =SUM(D31:O31) -> 0
A32: Energia Elétrica | D32: 120 | E32: 120 | F32: 120 | G32: 120 | H32: 120 | I32: 120 | J32: 120 | K32: 120 | L32: 120 | M32: 120 | N32: 120 | O32: 120 | P32: =SUM(D32:O32) -> 1440
A33: Despesas de depreciação | D33: 250 | E33: 250 | F33: 250 | G33: 250 | H33: 250 | I33: 250 | J33: 250 | K33: 250 | L33: 250 | M33: 250 | N33: 250 | O33: 250 | P33: =SUM(D33:O33) -> 3000
A34: Outras Despesas | D34: 400 | E34: 400 | F34: 400 | G34: 400 | H34: 400 | I34: 400 | J34: 400 | K34: 400 | L34: 400 | M34: 400 | N34: 400 | O34: 400 | P34: =SUM(D34:O34) -> 4800

Sheet Resumo-Planejamento Financeiro
A1: Demonstração do Resultado do Exercício
B3: Ano 01 | C3: Ano 02 | D3: Ano 03 | E3: Ano 04 | F3: Ano 05
A4: Receitas Brutas | B4: ='Entrada de $'!N5 -> 171898 | C4: =B4*(1+InformacoesBasicas!D29) -> 343796 | D4: =C4*(1+InformacoesBasicas!D30) -> 567263.4 | E4: =D4*(1+InformacoesBasicas!D31) -> 709079.25 | F4: =E4*(1+InformacoesBasicas!D32) -> 744533.21
A5: (-) Impostos | B5: =IF(InformacoesBasicas!$B10=1,0.18,IF(InformacoesBasicas!$B10=2,0.05,IF(InformacoesBasicas!$B10=1,0.1,0.1)))*B4 -> 8594.9 | C5: =IF(InformacoesBasicas!$B10=1,0.18,IF(InformacoesBasicas!$B10=2,0.05,IF(InformacoesBasicas!$B10=1,0.1,0.1)))*C4 -> 17189.8 | D5: =IF(InformacoesBasicas!$B10=1,0.18,IF(InformacoesBasicas!$B10=2,0.05,IF(InformacoesBasicas!$B10=1,0.1,0.1)))*D4 -> 28363.17 | E5: =IF(InformacoesBasicas!$B10=1,0.18,IF(InformacoesBasicas!$B10=2,0.05,IF(InformacoesBasicas!$B10=1,0.1,0.1)))*E4 -> 35453.963 | F5: =IF(InformacoesBasicas!$B10=1,0.18,IF(InformacoesBasicas!$B10=2,0.05,IF(InformacoesBasicas!$B10=1,0.1,0.1)))*F4 -> 37226.661
A6: Receitas Líquidas | B6: =B4-B5 -> 163303.1 | C6: =C4-C5 -> 326606.2 | D6: =D4-D5 -> 538900.23 | E6: =E4-E5 -> 673625.29 | F6: =F4-F5 -> 707306.55
A7: (-)Custo das Mercadorias Vendidas | B7: ='Calculo de Custo'!N6 -> 34502 | C7: =B7*(1+InformacoesBasicas!D43) -> 38297.22 | D7: =C7*(1+InformacoesBasicas!D44) -> 42509.914 | E7: =D7*(1+InformacoesBasicas!D45) -> 47186.005 | F7: =E7*(1+InformacoesBasicas!D46) -> 52376.465
A8: (-) Despesas Operacionais | B8: ='Saídas de $'!P22 -> 235840 | C8: =B8*(1+InformacoesBasicas!D36) -> 306592 | D8: =C8*(1+InformacoesBasicas!D37) -> 352580.8 | E8: =D8*(1+InformacoesBasicas!D38) -> 370209.84 | F8: =E8*(1+InformacoesBasicas!D39) -> 370209.84
A9: Resultado antes do IR | B9: =B6-B8-B7 -> -107038.9 | C9: =C6-C8-C7 -> -18283.02 | D9: =D6-D8-D7 -> 143809.52 | E9: =E6-E8-E7 -> 256229.44 | F9: =F6-F8-F7 -> 284720.25
A10: (-) Imposto de Renda | B10: =IF(B9>0,B9*0.25,0) -> 0 | C10: =IF(C9>0,C9*0.25,0) -> 0 | D10: =IF(D9>0,D9*0.25,0) -> 35952.379 | E10: =IF(E9>0,E9*0.25,0) -> 64057.361 | F10: =IF(F9>0,F9*0.25,0) -> 71180.062
A11: Lucro/Prejuízo Líquido | B11: =B9-B10 -> -107038.9 | C11: =C9-C10 -> -18283.02 | D11: =D9-D10 -> 107857.14 | E11: =E9-E10 -> 192172.08 | F11: =F9-F10 -> 213540.18
A14: Demonstração do Fluxo de Caixa
B15: Ano 01 | C15: Ano 02 | D15: Ano 03 | E15: Ano 04 | F15: Ano 05
A16: Entradas | B16: =B4 -> 171898 | C16: =C4 -> 343796 | D16: =D4 -> 567263.4 | E16: =E4 -> 709079.25 | F16: =F4 -> 744533.21
A17: (-) Saídas | B17: =B5+B8+B10+B7+'Saídas de $'!B5 -> 422736.9 | C17: =C5+C8+C10+C7 -> 362079.02 | D17: =D5+D8+D10+D7 -> 459406.26 | E17: =E5+E8+E10+E7 -> 516907.17 | F17: =F5+F8+F10+F7 -> 530993.03
A18: (+) Depreciação | B18: =SUM('Saídas de $'!C$10:$C$12) -> 3000 | C18: =SUM('Saídas de $'!$C$10:D$12) -> 3000 | D18: =SUM('Saídas de $'!$C$10:E$12) -> 3000 | E18: =SUM('Saídas de $'!$C$10:F$12) -> 3000 | F18: =SUM('Saídas de $'!$C$10:G$12) -> 3000
A19: Fluxo de Caixa | B19: =B16-B17+B18 -> -247838.9 | C19: =C16-C17+C18 -> -15283.02 | D19: =D16-D17+D18 -> 110857.14 | E19: =E16-E17+E18 -> 195172.08 | F19: =F16-F17+F18 -> 216540.18
A23: Taxa Interna de Retorno Estimada: | C23: =IRR(B56:G56) -> 0.20568019 | D23: ao ano
A55: Necessidade de Investimento | B55: Ano 0 | C55: Ano 1 | D55: Ano 2 | E55: Ano 3 | F55: Ano 4 | G55: Ano 5
A56: Fluxo de Caixa | B56: =-'Saídas de $'!B8 -> -143800 | C56: =B11+'Saídas de $'!$P33 -> -104038.9 | D56: =C11+'Saídas de $'!$P33 -> -15283.02 | E56: =D11+'Saídas de $'!$P33 -> 110857.14 | F56: =E11+'Saídas de $'!$P33 -> 195172.08 | G56: =F11+'Saídas de $'!$P33 -> 216540.18

Sheet Premissas e Modelo
A1: EcoTracker — Modelo de Negócio e Premissas da Análise Financeira
A3: Usuário | B3: Cidadão urbano que monitora pegada de carbono, qualidade do ar e hábitos sustentáveis pelo app Android (gratuito, com gamificação e Eco-Pontos).
A4: Pagador | B4: Três pagadores distintos do usuário gratuito: (1) o próprio usuário quando migra para o plano Premium; (2) empresas que licenciam a API EcoTracker Compliance para gestão ESG; (3) marcas patrocinadoras e projetos de compensação de carbono.
A5: Proposta de valor | B5: Para o cidadão: medir e reduzir o próprio impacto ambiental com dados reais de qualidade do ar e recompensas. Para a empresa: relatórios e trilha de auditoria ESG prontos, via API REST, sem construir sistema próprio.
A6: Core do negócio | B6: A plataforma de dados ambientais (API .NET 8 + base de emissões, licenças, auditorias e alertas). O app é o canal de aquisição; o core que gera margem é o dado e a automação do compliance.
A7: Monetização | B7: Freemium: app gratuito → Assinatura Premium R$ 7,90/mês; Licença B2B R$ 890/mês por empresa; Patrocínio de conteúdo R$ 2.500/mês por marca; Comissão média de R$ 25 por transação de compensação de carbono.
A8: Atividades que roubam escala | B8: Onboarding manual de clientes B2B, suporte 1:1, produção artesanal de conteúdo patrocinado e integrações sob medida. Mitigação: autosserviço via Swagger/documentação, base de conhecimento, templates de relatório e planos padronizados.
A9: Parceiros | B9: OpenWeatherMap (dados de qualidade do ar), provedor de nuvem (créditos para startups), processadora de pagamentos/Google Play, consultorias ESG e certificadoras de projetos de carbono como canal B2B.
A10: Evolução das receitas | B10: Ano 1: validação com Premium + primeiros contratos B2B. Anos 2-3: escala do B2B (+100% e +65% de vendas), marketplace de compensação e novos módulos (Scope 3, dashboards). Anos 4-5: maturidade, crescimento de 25% e 5% com base instalada e reajuste de preços.
A12: Premissas dos números
A13: Volumes do Ano 1 | B13: Premium partindo do mês 3 e chegando a 2.300 assinantes ativos no mês 12 (conversão de ~7% sobre a base gratuita projetada); B2B a partir do mês 6, chegando a 6 contas; 3 patrocinadores no fim do ano; 1.000 transações de compensação no ano.
A14: Custos diretos | B14: R$ 1,10 por assinante/mês (nuvem + APIs), R$ 120 por licença B2B/mês (infra dedicada e suporte), R$ 300 por patrocínio (produção de conteúdo) e R$ 15 por transação de compensação (repasse ao certificador).
A15: Investimento inicial | B15: R$ 143.800 — desenvolvimento do app Android, app iOS, site e sistema web/API, equipamentos, móveis, abertura da empresa e assessoria jurídica (contratos e LGPD).
A16: Despesas operacionais | B16: Equipe enxuta (R$ 8 mil/mês no 1º semestre e R$ 12 mil/mês no 2º), pró-labore de R$ 2,5 mil/mês, marketing crescente de R$ 2 mil a R$ 5 mil/mês, nuvem, contabilidade, coworking a partir do mês 7 e depreciação de R$ 3 mil/ano.
A17: Tributação | B17: Simples Nacional — 5% sobre a receita bruta de serviços e 25% de IR sobre o lucro, conforme o template.
A18: Resultado | B18: Prejuízo nos Anos 1 e 2 (investimento em aquisição), lucro a partir do Ano 3, payback do investimento no Ano 4 e TIR estimada de ~20,6% ao ano em 5 anos.
A20: Observação | B20: Projeção elaborada com premissas estimadas pela equipe a partir da pesquisa com 67 respondentes (59% pagariam por um plano premium) e de preços praticados no mercado; não representa resultados realizados.
